ndtree/__init__.py
ndtree/ndTree.py
ndtree-0.1.dist-info/DESCRIPTION.rst
ndtree-0.1.dist-info/METADATA
ndtree-0.1.dist-info/RECORD
ndtree-0.1.dist-info/WHEEL
ndtree-0.1.dist-info/metadata.json
ndtree-0.1.dist-info/top_level.txt
